{"entities":[{"end":5,"entity":"state","raw_end":5,"raw_start":0,"raw_value":"ligar","start":0,"value":"ligar"},{"end":19,"entity":"name","raw_end":19,"raw_start":6,"raw_value":"luz do quarto","start":6,"value":"luz do quarto"}],"intent":{"confidence":1.0,"name":"ChangeLightState"},"raw_text":"ligar luz do quarto","raw_tokens":["ligar","luz","do","quarto"],"recognize_seconds":0.046465255989460275,"slots":{"name":"luz do quarto","state":"ligar"},"speech_confidence":1,"text":"ligar luz do quarto","tokens":["ligar","luz","do","quarto"],"wakewordId":""}